tests/integration/__init__.py
tests/integration/cache.py
tests/integration/conftest.py
tests/integration/context.py
tests/integration/settings.py
tests/mock/__init__.py
tests/mock/fallback.py
tests/performance/__init__.py
tests/performance/check.py
tests/unit/__init__.py
tests/unit/application.py
tests/unit/context.py
tests/unit/decoration.py
tests/unit/language.py
tests/unit/legacy.py
tests/unit/logger.py
tests/unit/monkeypatch.py
tests/unit/render.py
tests/unit/api/__init__.py
tests/unit/api/client.py
tests/unit/api/pagination.py
tests/unit/api/snapshot.py
tests/unit/dictionary/__init__.py
tests/unit/dictionary/language.py
tests/unit/dictionary/snapshot.py
tests/unit/dictionary/source.py
tests/unit/dictionary/translations.py
tests/unit/ext/__init__.py
tests/unit/ext/date.py
tests/unit/ext/datetime.py
tests/unit/ext/list.py
tests/unit/ext/str.py
tests/unit/native_decoration/__init__.py
tests/unit/native_decoration/html.py
tests/unit/rules/__init__.py
tests/unit/rules/case.py
tests/unit/rules/engine.py
tests/unit/rules/functions.py
tests/unit/rules/options.py
tests/unit/rules/parser.py
tests/unit/rules/contexts/__init__.py
tests/unit/rules/contexts/count.py
tests/unit/rules/contexts/date.py
tests/unit/rules/contexts/gender.py
tests/unit/rules/contexts/genders.py
tests/unit/rules/contexts/number.py
tests/unit/token/__init__.py
tests/unit/token/data.py
tests/unit/token/method.py
tests/unit/token/parser.py
tests/unit/token/transform.py
tests/unit/tokenizers/__init__.py
tests/unit/tokenizers/data.py
tests/unit/tokenizers/dom.py
tests/unit/tools/__init__.py
tests/unit/tools/viewing_user.py
tests/unit/translation/__init__.py
tests/unit/translation/missed.py
tests/unit/web_tools/__init__.py
tests/unit/web_tools/tml_cookies.py
tests/unit/web_tools/translator.py
tml/__init__.py
tml/application.py
tml/base.py
tml/cache.py
tml/commands.py
tml/config.py
tml/context.py
tml/exceptions.py
tml/language.py
tml-0.3.1.dist-info/DESCRIPTION.rst
tml-0.3.1.dist-info/METADATA
tml-0.3.1.dist-info/metadata.json
tml-0.3.1.dist-info/RECORD
tml-0.3.1.dist-info/top_level.txt
tml-0.3.1.dist-info/WHEEL
