Metadata-Version: 2.0
Name: tml
Version: 0.3.1
Summary: Python SDK for tranlationexchange.com
Home-page: https://github.com/translationexchange/tml-python.git
Author: Translation Exchange, Inc.
Author-email: r.kamun@gmail.com
License: MIT
Keywords: tml tml-python translationexchange
Platform: UNKNOWN
Classifier: Development Status :: 3 - Alpha
Classifier: Intended Audience :: Developers
Classifier: Topic :: Software Development :: Build Tools
Classifier: License :: OSI Approved :: MIT License
Classifier: Programming Language :: Python :: 2
Classifier: Programming Language :: Python :: 2.6
Classifier: Programming Language :: Python :: 2.7
Classifier: Programming Language :: Python :: 3
Classifier: Programming Language :: Python :: 3.3
Classifier: Programming Language :: Python :: 3.4
Classifier: Programming Language :: Python :: 3.5
Requires-Dist: requests (==2.7.0)
Requires-Dist: six (==1.10.0)
Requires-Dist: lxml (==3.6.0)
Provides-Extra: memcached
Requires-Dist: python-memcached (>=1.57); extra == 'memcached'
Provides-Extra: pylibmc
Requires-Dist: pylibmc (>=1.5.0); extra == 'pylibmc'
Provides-Extra: redis
Requires-Dist: redis (==2.10.5); extra == 'redis'
